{
    "56B83539": {
        "long": "102 Dalmatians - Puppies to the Rescue (USA, Europe)",
        "short": "102 Dalmatians - Puppies to the Rescue"
    },
    "5692E262": {
        "long": "Buffy the Vampire Slayer (USA, Europe)",
        "short": "Buffy the Vampire Slayer"
    },
    "5622B551": {
        "long": "Bundesliga Stars 2001 (Germany)",
        "short": "Bundesliga Stars 2001"
    },
    "565FEC36": {
        "long": "Dance Dance Revolution GB 2 (Japan)",
        "short": "Dance Dance Revolution GB 2"
    },
    "56095F86": {
        "long": "Diva Starz (Germany)",
        "short": "Diva Starz"
    },
    "56F52663": {
        "long": "Network Boukenki Bugsite - Beta Version (Japan)",
        "short": "Network Boukenki Bugsite - Beta Version"
    },
    "56D76BA2": {
        "long": "Qui Qui (Japan) (GB Compatible)",
        "short": "Qui Qui"
    },
    "56BEB694": {
        "long": "Walt Disney World Quest - Magical Racing Tour (USA, Europe)",
        "short": "Walt Disney World Quest - Magical Racing Tour"
    },
    "560D71EB": {
        "long": "Lemmings (Europe) (Rev 1)",
        "short": "Lemmings"
    },
    "562C8F7F": {
        "long": "Momotarou Collection 2 (Japan) (SGB Enhanced)",
        "short": "Momotarou Collection 2"
    },
    "56BA6A71": {
        "long": "Monster Maker - Barcode Saga (Japan)",
        "short": "Monster Maker - Barcode Saga"
    },
    "56410442": {
        "long": "Shippo de Bun (Japan)",
        "short": "Shippo de Bun"
    },
    "56AFCA4C": {
        "long": "Tokoro's Mahjong Jr. (Japan) (SGB Enhanced)",
        "short": "Tokoro's Mahjong Jr."
    },
    "56800C6B": {
        "long": "Urusei Yatsura - Miss Tomobiki o Sagase! (Japan)",
        "short": "Urusei Yatsura - Miss Tomobiki o Sagase!"
    }
}