{
    "570BAFDB": {
        "long": "Bakusou Senki Metal Walker GB - Koutetsu no Yuujou (Japan) (Rev 1) (Proto) (GB Compatible)",
        "short": "Bakusou Senki Metal Walker GB - Koutetsu no Yuujou"
    },
    "57F1A202": {
        "long": "Barbie - Magic Genie Adventure (USA)",
        "short": "Barbie - Magic Genie Adventure"
    },
    "57EA1EC8": {
        "long": "International Superstar Soccer 2000 (Europe)",
        "short": "International Superstar Soccer 2000"
    },
    "577E1521": {
        "long": "Klustar (Europe) (En,Fr,De,Es,It) (GB Compatible)",
        "short": "Klustar"
    },
    "5715D896": {
        "long": "Legend of Zelda, The - Link's Awakening DX (USA, Europe) (Rev 2) (Beta) (1999-09-07) (SGB Enhanced) (GB Compatible)",
        "short": "Legend of Zelda, The - Link's Awakening DX"
    },
    "573613D7": {
        "long": "Pocket Puyo Puyo-n (Japan) (Rev 2)",
        "short": "Pocket Puyo Puyo-n"
    },
    "576F5CED": {
        "long": "Pokemon - Silberne Edition (Germany) (Beta) (SGB Enhanced) (GB Compatible)",
        "short": "Pokemon - Silberne Edition"
    },
    "57F82031": {
        "long": "RPG Tsukuru GB (Japan) (Rev 1) (NP)",
        "short": "RPG Tsukuru GB"
    },
    "5730393D": {
        "long": "Shaman King Card Game - Chou Senjiryakketsu - Meramera Hen (Japan)",
        "short": "Shaman King Card Game - Chou Senjiryakketsu - Meramera Hen"
    },
    "5784BCE0": {
        "long": "Towers II - Plight of the Stargazer (USA) (Proto 1) (2000-05-07)",
        "short": "Towers II - Plight of the Stargazer"
    },
    "5721E7D6": {
        "long": "Konamic Sports in Barcelona (Japan)",
        "short": "Konamic Sports in Barcelona"
    },
    "57BA5D56": {
        "long": "Mortal Kombat II - Kyuukyoku Shinken (Japan)",
        "short": "Mortal Kombat II - Kyuukyoku Shinken"
    },
    "57D95C92": {
        "long": "Mystic Quest (Europe)",
        "short": "Mystic Quest"
    },
    "57E9C17D": {
        "long": "Purikura Pocket - Fukanzen Joshikousei Manual (Japan) (Rev 1) (NP)",
        "short": "Purikura Pocket - Fukanzen Joshikousei Manual"
    },
    "575D6D9D": {
        "long": "Sa-Ga 3 - Jikuu no Hasha (Japan)",
        "short": "Sa-Ga 3 - Jikuu no Hasha"
    },
    "57D21EF4": {
        "long": "World Soccer GB (Japan) (SGB Enhanced)",
        "short": "World Soccer GB"
    }
}