{
    "A4C6523D": {
        "long": "Bob et Bobette - Les Dompteurs du Temps (Europe) (Fr,Nl)",
        "short": "Bob et Bobette - Les Dompteurs du Temps"
    },
    "A4DDE805": {
        "long": "From TV Animation One Piece - Yume no Luffy Kaizokudan Tanjou! (Japan) (Rev 1) (SGB Enhanced) (GB Compatible)",
        "short": "From TV Animation One Piece - Yume no Luffy Kaizokudan Tanjou!"
    },
    "A41ED926": {
        "long": "Jeff Gordon XS Racing (USA) (GB Compatible)",
        "short": "Jeff Gordon XS Racing"
    },
    "A4CD26FF": {
        "long": "Super Mario Bros. Deluxe (USA, Europe)",
        "short": "Super Mario Bros. Deluxe"
    },
    "A4D06001": {
        "long": "Yu-Gi-Oh! Duel Monsters 4 - Battle of Great Duelist - Kaiba Deck (Japan)",
        "short": "Yu-Gi-Oh! Duel Monsters 4 - Battle of Great Duelist - Kaiba Deck"
    },
    "A4CC3C3A": {
        "long": "Asterix (USA) (Proto 3)",
        "short": "Asterix"
    },
    "A42524A3": {
        "long": "Doraemon - Taiketsu HimitsuDougu!! (Japan)",
        "short": "Doraemon - Taiketsu HimitsuDougu!!"
    }
}