{
    "DEFF8DFB": {
        "long": "All Star Tennis 2000 (Europe) (AZTX) (Proto) (GB Compatible)",
        "short": "All Star Tennis 2000"
    },
    "DE390609": {
        "long": "Dragon Tales - Dragon Adventures (USA)",
        "short": "Dragon Tales - Dragon Adventures"
    },
    "DE7505C0": {
        "long": "Gem Gem Monster (Japan) (SGB Enhanced) (GB Compatible)",
        "short": "Gem Gem Monster"
    },
    "DE52FFDC": {
        "long": "Kindaichi Shounen no Jikenbo - 10 Nenme no Shoutaijou (Japan) (SGB Enhanced) (GB Compatible)",
        "short": "Kindaichi Shounen no Jikenbo - 10 Nenme no Shoutaijou"
    },
    "DE1338D2": {
        "long": "Madden NFL 2002 (USA)",
        "short": "Madden NFL 2002"
    },
    "DE04772F": {
        "long": "Montezuma's Return! (USA) (En,Es) (GB Compatible)",
        "short": "Montezuma's Return!"
    },
    "DEE71D44": {
        "long": "Pocket King (Japan) (SGB Enhanced) (GB Compatible)",
        "short": "Pocket King"
    },
    "DEC1260E": {
        "long": "Sonic Adventure 7 (Taiwan) (En) (Unl)",
        "short": "Sonic Adventure 7"
    },
    "DE459A47": {
        "long": "Batman - Return of the Joker (Japan)",
        "short": "Batman - Return of the Joker"
    },
    "DEE05370": {
        "long": "Metroid II - Return of Samus (World)",
        "short": "Metroid II - Return of Samus"
    },
    "DEACE430": {
        "long": "Pachi-Slot Kids 2 (Japan)",
        "short": "Pachi-Slot Kids 2"
    },
    "DE383E73": {
        "long": "TaleSpin (USA)",
        "short": "TaleSpin"
    },
    "DE398678": {
        "long": "Xenon 2 (USA, Europe)",
        "short": "Xenon 2"
    }
}